README.md
setup.py
accordion/__init__.py
accordion.egg-info/PKG-INFO
accordion.egg-info/SOURCES.txt
accordion.egg-info/dependency_links.txt
accordion.egg-info/requires.txt
accordion.egg-info/top_level.txt
tests/__init__.py
tests/test_all.py